pi_network_helper/__init__.py
pi_network_helper/pi_network.py
pi_network_helper-0.1.dist-info/LICENSE
pi_network_helper-0.1.dist-info/METADATA
pi_network_helper-0.1.dist-info/WHEEL
pi_network_helper-0.1.dist-info/top_level.txt
pi_network_helper-0.1.dist-info/RECORD
