Metadata-Version: 2.1
Name: pi-network-helper
Version: 0.1
Summary: A library for interacting with Pi Network API
Home-page: https://github.com/roniahmadi/pi_network_helper
Author: Roni Ahmadi
Author-email: roniahmadi30@gmail.com
License: MIT
Classifier: Development Status :: 3 - Alpha
Classifier: Intended Audience :: Developers
Classifier: License :: OSI Approved :: MIT License
Classifier: Programming Language :: Python :: 3
Classifier: Programming Language :: Python :: 3.8
Classifier: Programming Language :: Python :: 3.9
Classifier: Programming Language :: Python :: 3.10
Classifier: Programming Language :: Python :: 3.11
License-File: LICENSE
Requires-Dist: requests
Requires-Dist: stellar-sdk
